only_train_once/__init__.py
only_train_once/assets/__init__.py
only_train_once/assets/group_types.py
only_train_once/assets/theme.py
only_train_once/compression/__init__.py
only_train_once/compression/compression.py
only_train_once/flops/__init__.py
only_train_once/flops/flops.py
only_train_once/graph/__init__.py
only_train_once/graph/connected_component.py
only_train_once/graph/graph.py
only_train_once/graph/node.py
only_train_once/operation/__init__.py
only_train_once/operation/operator.py
only_train_once/operation/operators_dict.py
only_train_once/optimizer/__init__.py
only_train_once/optimizer/dhspg.py
only_train_once/transform/__init__.py
only_train_once/transform/ge.py
only_train_once/transform/onnx_graph_transform.py
only_train_once/transform/transforms.py
only_train_once/zig/__init__.py
only_train_once/zig/zig.py
otoML/__init__.py
otoML/assets/__init__.py
otoML/assets/group_types.py
otoML/assets/theme.py
otoML/compression/__init__.py
otoML/compression/compression.py
otoML/flops/__init__.py
otoML/flops/flops.py
otoML/graph/__init__.py
otoML/graph/connected_component.py
otoML/graph/graph.py
otoML/graph/node.py
otoML/operation/__init__.py
otoML/operation/operator.py
otoML/operation/operators_dict.py
otoML/optimizer/__init__.py
otoML/optimizer/dhspg.py
otoML/transform/__init__.py
otoML/transform/ge.py
otoML/transform/onnx_graph_transform.py
otoML/transform/transforms.py
otoML/zig/__init__.py
otoML/zig/zig.py
otoml/__init__.py
otoml/assets/__init__.py
otoml/assets/group_types.py
otoml/assets/theme.py
otoml/compression/__init__.py
otoml/compression/compression.py
otoml/flops/__init__.py
otoml/flops/flops.py
otoml/graph/__init__.py
otoml/graph/connected_component.py
otoml/graph/graph.py
otoml/graph/node.py
otoml/operation/__init__.py
otoml/operation/operator.py
otoml/operation/operators_dict.py
otoml/optimizer/__init__.py
otoml/optimizer/dhspg.py
otoml/transform/__init__.py
otoml/transform/ge.py
otoml/transform/onnx_graph_transform.py
otoml/transform/transforms.py
otoml-2.0.1.dist-info/LICENSE
otoml-2.0.1.dist-info/METADATA
otoml-2.0.1.dist-info/WHEEL
otoml-2.0.1.dist-info/top_level.txt
otoml-2.0.1.dist-info/RECORD
