Metadata-Version: 2.1
Name: otoml
Version: 2.0.1
Summary: Only Train Once (OTO): Automatic One-Shot General DNN Training and Compression Framework
Home-page: https://github.com/tianyic/only_train_once
Author: Tianyi Chen
Author-email: tiachen@microsoft.com
License: MIT
Keywords: automatic,one-shot,structure pruning,sparse optimization
Platform: UNKNOWN
Classifier: Development Status :: 3 - Alpha
Classifier: Intended Audience :: Developers
Classifier: License :: OSI Approved :: MIT License
Classifier: Programming Language :: Python :: 3
License-File: LICENSE
Requires-Dist: onnx (>=1.12.*)
Requires-Dist: onnxruntime (>=1.12.*)
Requires-Dist: numpy (>=1.22.*)
Requires-Dist: graphviz (>=0.20)
Requires-Dist: pydot (>=1.4)
